<?xml version="1.0" encoding="UTF-8" ?><dbgapss xmlns:xsi="http://www.w3.org/2001/XMLSchema-instance" xsi:noNamespaceSchemaLocation="dbgapssws.1.0.xsd"><Study uid="42061" whole_study_id="42061" phs="002444" v="1" p="1" createDate="2021-05-21T12:54:14-05:00" completedByGPADate="2021-05-27T09:23:57-05:00" modDate="2021-08-11T22:29:55-05:00" maxParentChildStudyModDate="2021-08-11T22:29:55-05:00" handle="CancerSusceptibilityOS" num_participants="1004"><StudyInfo accession="phs002444.v1.p1" parentAccession="phs002444.v1.p1"><BioProject id="PRJNA733249" entrez_id="733249" type="bp_admin_access"/><BioProject id="PRJNA733250" entrez_id="733250" type="bp_data_submission"/><StudyNameEntrez>Germline Genetic Variants in Cancer-Susceptibility Genes in Patients With Osteosarcoma</StudyNameEntrez><StudyTypes2 calculated="Yes"><StudyType21 name="phenotype_data" chosen="Yes"/><StudyType21 name="analysis" chosen="No"/><StudyType21 name="individual_sequencing" chosen="Yes"><StudyType22 name="ncbi_for_sequence"/><StudyType22 name="whole_targ_exome"/></StudyType21><StudyType21 name="supporting_documents" chosen="No"/><StudyType21 name="images" chosen="No"/><StudyType21 name="molecular" chosen="No"/><StudyType21 name="subject_samples" chosen="Yes"><StudyType22 name="germline"/></StudyType21><StudyType21 name="links_to_ncbi_dbs" chosen="No"/><StudyType21 name="other_general" chosen="No"/></StudyTypes2><StudyTypes><StudyType>phenotype_data</StudyType><StudyType>individual_sequencing</StudyType><StudyType>germline</StudyType><StudyType>whole_exome</StudyType><StudyType>sra</StudyType></StudyTypes><SraStorages><SraStorage location="NCBI"/></SraStorages></StudyInfo><Authority><ICs><IC id="4" name="NCI" is_funding_ic="true" is_admin_ic="true" primary="true"/></ICs><Persons><Person nedid="0013514277" aid="1" auth="cit" login="mirabellol" fname="Lisa" mname="J" lname="Mirabello" email="mirabellol@mail.nih.gov"><Role allow_direct_access="true">PI</Role><Organization>NIH</Organization></Person><Person nedid="0011217741" aid="1" auth="cit" login="tobiasg" fname="Geoffrey" mname="Scott" lname="Tobias" email="tobiasg@mail.nih.gov"><Role>PI_ASSIST</Role><Organization>NIH</Organization></Person><Person nedid="0013269007" aid="1" auth="cit" login="kianga" fname="Anne" mname="" lname="Sturcke" email="kianga@ncbi.nlm.nih.gov"><Role>PHENO_CURATOR</Role><Organization>NIH</Organization></Person><Person nedid="2002647128" aid="1" auth="cit" login="guptan11" fname="Neha" mname="" lname="Gupta" email="neha.gupta2@nih.gov"><Role>GENO_CURATOR</Role><Organization>NIH</Organization></Person><Person nedid="0011217741" aid="1" auth="cit" login="tobiasg" fname="Geoffrey" mname="Scott" lname="Tobias" email="tobiasg@mail.nih.gov"><Role>GPA</Role><Organization>NIH</Organization></Person></Persons></Authority><Policy display-research-statement="true" display-public-summary="true" years-until-renewal="1" weeks-to-cancel-request="8" pub-embargo="none"><acknowledgement_statement>This study was funded by the intramural research program of the Division of Cancer Epidemiology and Genetics, National Cancer Institute, National Institutes of Health. This work was supported by the National Cancer Institute (CA55727, G.T. Armstrong, Principal Investigator). Support to St. Jude Children&#8217;s Research Hospital also provided by the Cancer Center Support (CORE) grant (CA21765, C. Roberts, Principal Investigator) and the American Lebanese-Syrian Associated Charities (ALSAC). This work was supported by grants to L.G.S. from the National Institutes of Health U01CA122371, and from The Zach Sobiech Osteosarcoma Fund of Children's Cancer Research Fund. University of Minnesota sequencing was funded by a 2013 Hyundai Hope of Wheels Grant in addition to the other sources. Research is supported by the Chair's Grant U10 CA98543 and Human Specimen Banking Grant U24 CA114766 of the Children's Oncology Group from the National Cancer Institute, National Institutes of Health, Bethesda, MD, USA. Additional support for research is provided by a grant from the WWWW (QuadW) Foundation, Inc. to the Children's Oncology Group. The work of A.P.G was supported by the Departamento De Salud, Gobierno De Navarra, Proyectos de Biomedicina 2018. A.P.G. was also funded by La Fundaci&#243;n "La Caixa&#8221;- Caja Navarra, PI13/01476, FIS, ISCIII. F.L. was funded by and AECC,  FIMA (Foundation for Applied Medical Research), Cancer Research Thematic Network of the Instituto de Salud Carlos III (RTICC RD 12/0036/0066), CIBERONC (CB16/12/00443 and CB16/12/00350) and the Spanish Ministry of Economy and Competitiveness (RTI2018-094507-B-100). This study was also supported by biobank grants from the Regione Emilia-Romagna, by the infrastructure and personnel of the Royal National Orthopaedic Hospital Musculoskeletal Research Programme and Biobank. Support was also provided to A.M.F. (UCL) by the National Institute for Health Research UCLH Biomedical Research Centre, and UCL Experimental Cancer Centre. The work of A.M.F. was supported by the Bone Cancer Research Trust UK. The International Sarcoma Kindred Study was supported by the Rainbows for Kate Foundation, the Liddy Shriver Sarcoma Initiative, the Victorian Cancer Agency, the Australian National Health and Medical Research Council (APP1004017) and Cancer Australia (APP1067094). </acknowledgement_statement><ic_specific_access_term/><DUC universal_duc="Yes"><File full_url="https://dbgap.ncbi.nlm.nih.gov/aa/docs/Static_DUC_20190419.pdf" filename="Static_DUC_20190419.pdf" content-type="application/pdf"/></DUC><DUC_PDF universal_duc="Yes"><File full_url="https://dbgap.ncbi.nlm.nih.gov/aa/docs/Static_DUC_20190419.pdf" filename="Static_DUC_20190419.pdf" content-type="application/pdf"/></DUC_PDF><GSR_Access gsr_mode="unrest_access" gsr_mode_label="Unrestricted access"/><ConsentGroup uid="4548" CGType="cg_class_HMB" title="Health/Medical/Biomedical" name="HMB" dac_uid="59" dac_name="NCI DAC" irb-approval-required="No"><Use-Restriction>Use of this data is limited to health/medical/biomedical purposes, does not include the study of population origins or ancestry.

</Use-Restriction></ConsentGroup></Policy><SRA/><Documents/><Status uid="1" name="released" title="Released"/></Study></dbgapss>